django_aws_utils/__init__.py
django_aws_utils/ec2_ip.py
django_aws_utils/secrets_manager.py
django_aws_utils-1.0.0.dist-info/LICENSE
django_aws_utils-1.0.0.dist-info/METADATA
django_aws_utils-1.0.0.dist-info/WHEEL
django_aws_utils-1.0.0.dist-info/top_level.txt
django_aws_utils-1.0.0.dist-info/RECORD
