Metadata-Version: 2.1
Name: django-aws-utils
Version: 1.0.0
Summary: Helpers for deploying Django on AWS
Home-page: https://github.com/vladvasiliu/django-aws-utils
Author: Vlad Vasiliu
Author-email: code@vladvasiliu.com
License: UNKNOWN
Project-URL: Source, https://github.com/vladvasiliu/django-aws-utils
Project-URL: Documentation, http://django-aws-utils.rtfd.io/
Platform: UNKNOWN
Classifier: License :: OSI Approved :: BSD License
Classifier: Development Status :: 5 - Production/Stable
Classifier: Environment :: Web Environment
Classifier: Framework :: Django
Classifier: Intended Audience :: Developers
Classifier: Operating System :: OS Independent
Classifier: Programming Language :: Python :: 3
Classifier: Topic :: Internet
Classifier: Topic :: Software Development :: Libraries :: Python Modules
Requires-Python: >=3.6
Requires-Dist: boto3
Requires-Dist: django
Requires-Dist: requests
